odoo10_addon_stock_orderpoint_manual_procurement-10.0.1.0.0.99.dev6-py3.8-nspkg.pth
odoo/addons/stock_orderpoint_manual_procurement/README.rst
odoo/addons/stock_orderpoint_manual_procurement/__init__.py
odoo/addons/stock_orderpoint_manual_procurement/__manifest__.py
odoo/addons/stock_orderpoint_manual_procurement/i18n/am.po
odoo/addons/stock_orderpoint_manual_procurement/i18n/ar.po
odoo/addons/stock_orderpoint_manual_procurement/i18n/bg.po
odoo/addons/stock_orderpoint_manual_procurement/i18n/bs.po
odoo/addons/stock_orderpoint_manual_procurement/i18n/ca.po
odoo/addons/stock_orderpoint_manual_procurement/i18n/ca_ES.po
odoo/addons/stock_orderpoint_manual_procurement/i18n/cs.po
odoo/addons/stock_orderpoint_manual_procurement/i18n/cs_CZ.po
odoo/addons/stock_orderpoint_manual_procurement/i18n/da.po
odoo/addons/stock_orderpoint_manual_procurement/i18n/de.po
odoo/addons/stock_orderpoint_manual_procurement/i18n/el_GR.po
odoo/addons/stock_orderpoint_manual_procurement/i18n/en_AU.po
odoo/addons/stock_orderpoint_manual_procurement/i18n/en_GB.po
odoo/addons/stock_orderpoint_manual_procurement/i18n/es.po
odoo/addons/stock_orderpoint_manual_procurement/i18n/es_AR.po
odoo/addons/stock_orderpoint_manual_procurement/i18n/es_CL.po
odoo/addons/stock_orderpoint_manual_procurement/i18n/es_CO.po
odoo/addons/stock_orderpoint_manual_procurement/i18n/es_CR.po
odoo/addons/stock_orderpoint_manual_procurement/i18n/es_DO.po
odoo/addons/stock_orderpoint_manual_procurement/i18n/es_EC.po
odoo/addons/stock_orderpoint_manual_procurement/i18n/es_ES.po
odoo/addons/stock_orderpoint_manual_procurement/i18n/es_MX.po
odoo/addons/stock_orderpoint_manual_procurement/i18n/es_PE.po
odoo/addons/stock_orderpoint_manual_procurement/i18n/es_PY.po
odoo/addons/stock_orderpoint_manual_procurement/i18n/es_VE.po
odoo/addons/stock_orderpoint_manual_procurement/i18n/et.po
odoo/addons/stock_orderpoint_manual_procurement/i18n/eu.po
odoo/addons/stock_orderpoint_manual_procurement/i18n/fa.po
odoo10_addon_stock_orderpoint_manual_procurement-10.0.1.0.0.99.dev6.dist-info/METADATA
odoo10_addon_stock_orderpoint_manual_procurement-10.0.1.0.0.99.dev6.dist-info/WHEEL
odoo10_addon_stock_orderpoint_manual_procurement-10.0.1.0.0.99.dev6.dist-info/namespace_packages.txt
odoo10_addon_stock_orderpoint_manual_procurement-10.0.1.0.0.99.dev6.dist-info/top_level.txt
odoo10_addon_stock_orderpoint_manual_procurement-10.0.1.0.0.99.dev6.dist-info/RECORD
